libsquiggly/__init__.py
libsquiggly/analysis/__init__.py
libsquiggly/analysis/matched_filter.py
libsquiggly/analysis/peak_suppression.py
libsquiggly/analysis/rolling_abs_mean.py
libsquiggly/instfreq/__init__.py
libsquiggly/instfreq/lpc.py
libsquiggly/instfreq/lsharm.py
libsquiggly/instfreq/maxpeak.py
libsquiggly/instfreq/peaktracing.py
libsquiggly/instfreq/talkbox/__init__.py
libsquiggly/instfreq/talkbox/info.py
libsquiggly/instfreq/talkbox/setup.py
libsquiggly/instfreq/talkbox/version.py
libsquiggly/instfreq/talkbox/features/__init__.py
libsquiggly/instfreq/talkbox/features/mel.py
libsquiggly/instfreq/talkbox/features/mfcc.py
libsquiggly/instfreq/talkbox/features/setup.py
libsquiggly/instfreq/talkbox/linpred/__init__.py
libsquiggly/instfreq/talkbox/linpred/_lpc.so
libsquiggly/instfreq/talkbox/linpred/common.py
libsquiggly/instfreq/talkbox/linpred/levinson_lpc.py
libsquiggly/instfreq/talkbox/linpred/py_lpc.py
libsquiggly/instfreq/talkbox/linpred/setup.py
libsquiggly/instfreq/talkbox/misc/__init__.py
libsquiggly/instfreq/talkbox/misc/peak_picking.py
libsquiggly/instfreq/talkbox/misc/setup.py
libsquiggly/instfreq/talkbox/spectral/__init__.py
libsquiggly/instfreq/talkbox/spectral/basic.py
libsquiggly/instfreq/talkbox/tools/__init__.py
libsquiggly/instfreq/talkbox/tools/cacorr.so
libsquiggly/instfreq/talkbox/tools/cffilter.so
libsquiggly/instfreq/talkbox/tools/correlations.py
libsquiggly/instfreq/talkbox/tools/ffilter.py
libsquiggly/instfreq/talkbox/tools/preprocess.py
libsquiggly/instfreq/talkbox/tools/segmentaxis.py
libsquiggly/instfreq/talkbox/tools/setup.py
libsquiggly/instfreq/talkbox/transforms/__init__.py
libsquiggly/instfreq/talkbox/transforms/dct.py
libsquiggly/instfreq/talkbox/transforms/dct_ref.py
libsquiggly/instfreq/talkbox/transforms/setup.py
libsquiggly/resampling/__init__.py
libsquiggly/resampling/fractional_shift.py
libsquiggly/resampling/halfbandfir.py
libsquiggly/resampling/resampling.py
libsquiggly-1.0.4.dist-info/DESCRIPTION.rst
libsquiggly-1.0.4.dist-info/METADATA
libsquiggly-1.0.4.dist-info/RECORD
libsquiggly-1.0.4.dist-info/WHEEL
libsquiggly-1.0.4.dist-info/metadata.json
libsquiggly-1.0.4.dist-info/top_level.txt
