Metadata-Version: 2.0
Name: libsquiggly
Version: 1.0.4
Summary: A toolbox to answer the age-old question "Why do the squiggly lines do what they do?"
Home-page: https://gitlab.cs.washington.edu/ubicomplab/libsquiggly
Author: Elliot Saba
Author-email: staticfloat@gmail.com
License: This software, unless otherwise noted, is released under the MIT license
Requires-Dist: matplotlib
Requires-Dist: numpy
Requires-Dist: scipy
